[
    {
        "_id": "ZazgEyytifHukhipY",
        "name": "成果 reprehenderit dolorem officia",
        "projectIds": "x3M2XsDhwe79js2xA"
    },
    {
        "_id": "5bWWg7g3qbgmTEmPt",
        "name": "成果 et reprehenderit voluptas",
        "projectIds": "Sr9XgnhH6ZfBwWYPX"
    },
    {
        "_id": "zo9DfrDzWLC9BHrQy",
        "name": "成果 et voluptatem voluptate",
        "projectIds": "wf5oXKTRxCp8qfN5c"
    },
    {
        "_id": "xQFhQ223RASAXzSJK",
        "name": "成果 commodi suscipit voluptatem",
        "userIds": "MT2BcwvE5QKNHkREf"
    },
    {
        "_id": "ZfByiZuNBzStZGhsw",
        "name": "成果 labore amet fugit",
        "userIds": "waALYRk2mACBxJWNd"
    },
    {
        "_id": "YK9kAoMrw4WRfGo59",
        "name": "成果 mollitia eligendi aut",
        "userIds": "ac86Yzrn54icxfywB"
    },
    {
        "_id": "cb3aynJT8ebvWvTCe",
        "name": "成果 aut voluptatem repellendus",
        "achievementIds": "xQFhQ223RASAXzSJK"
    },
    {
        "_id": "LenrgEzdqdJ5MhaQS",
        "name": "成果 aut fugiat quis",
        "achievementIds": "ZfByiZuNBzStZGhsw"
    },
    {
        "_id": "5yQG2qgkMLZZKa3G8",
        "name": "成果 ab tempora quisquam",
        "achievementIds": "YK9kAoMrw4WRfGo59"
    },
    {
        "_id": "LC6LSs9nu7S6EfPtq",
        "name": "成果 temporibus dolor et",
        "conversionIds": "xdHZ5jSeiQcBW5EiZ"
    },
    {
        "_id": "TaqRMtRszBDReYkMB",
        "name": "成果 molestiae nobis excepturi",
        "conversionIds": "PCZjJP5ftJ44adD4F"
    },
    {
        "_id": "TZD8oZEbnbrjrp23C",
        "name": "成果 odit et sequi",
        "conversionIds": "SYB5L7hxbb3DT9Qwv"
    },
    {
        "_id": "7vjhu3PkYRbJFcrk7",
        "name": "成果 reprehenderit minus nesciunt",
        "achievementIds": "LC6LSs9nu7S6EfPtq"
    },
    {
        "_id": "jC5wJkktmwZ8KG2kY",
        "name": "成果 ducimus error sit",
        "achievementIds": "TaqRMtRszBDReYkMB"
    },
    {
        "_id": "x29jYyHqtxsKqgN5Z",
        "name": "成果 dignissimos ut id",
        "achievementIds": "TZD8oZEbnbrjrp23C"
    }
]
